gitfluencer/__init__.py
gitfluencer/app.py
gitfluencer-0.1.4.1.dist-info/METADATA
gitfluencer-0.1.4.1.dist-info/WHEEL
gitfluencer-0.1.4.1.dist-info/entry_points.txt
gitfluencer-0.1.4.1.dist-info/top_level.txt
gitfluencer-0.1.4.1.dist-info/RECORD
