Metadata-Version: 2.1
Name: gitfluencer
Version: 0.1.4.1
Summary: Utility tool for interacting with the GitHub platform
Home-page: https://github.com/jjoeldaniel/gitfluencer
Author: jjoeldaniel
Author-email: joeldanielrico@gmail.com
Keywords: github,social
Classifier: Development Status :: 3 - Alpha
Classifier: Environment :: Console
Classifier: Intended Audience :: Developers
Classifier: License :: OSI Approved :: MIT License
Classifier: Programming Language :: Python :: 3
Classifier: Programming Language :: Python :: 3.6
Classifier: Programming Language :: Python :: 3.7
Classifier: Programming Language :: Python :: 3.8
Classifier: Programming Language :: Python :: 3.9
Classifier: Programming Language :: Python :: 3.10
Classifier: Programming Language :: Python :: 3.11
Requires-Dist: PyGithub
Requires-Dist: Requests
Requires-Dist: rich
